lawwenda/.pylintrc
lawwenda/__init__.py
lawwenda/lawwenda_cli.py
lawwenda/app/__init__.py
lawwenda/app/main_app.py
lawwenda/app/fm_app/__init__.py
lawwenda/app/fm_app/-templates/base.html
lawwenda/app/fm_app/-templates/index.html
lawwenda/app/http_webdav_app/__init__.py
lawwenda/app/http_webdav_app/davprop.py
lawwenda/asset/__init__.py
lawwenda/asset/data.py
lawwenda/asset/project_info.py
lawwenda/asset/-static/lawwenda.png
lawwenda/asset/-static/lawwenda.wsgi
lawwenda/asset/-static/web/.eslintrc.js
lawwenda/asset/-static/web/backend/common.js
lawwenda/asset/-static/web/components/detailspanel.js
lawwenda/asset/-static/web/components/directoryview.js
lawwenda/asset/-static/web/components/locationbar.js
lawwenda/asset/-static/web/components/notification.js
lawwenda/asset/-static/web/components/searchpanel.js
lawwenda/asset/-static/web/img/dir.svg
lawwenda/asset/-static/web/img/file.svg
lawwenda/asset/-static/web/img/lawwenda.png
lawwenda/asset/-static/web/pageresources/base.css
lawwenda/asset/-static/web/pageresources/index.css
lawwenda/asset/-static/web/pageresources/index.js
lawwenda/asset/-static/web/piweb/README~~piget
lawwenda/asset/-static/web/piweb/animation.js
lawwenda/asset/-static/web/piweb/busy.js
lawwenda/asset/-static/web/piweb/comm.js
lawwenda/asset/-static/web/piweb/conversationdialog.js
lawwenda/asset/-static/web/piweb/dialog.js
lawwenda/asset/-static/web/piweb/mapview.js
lawwenda/asset/-static/web/piweb/styling.js
lawwenda/asset/-static/web/piweb/.piget/name
lawwenda/asset/-static/web/piweb/.piget/piget_v1
lawwenda/asset/-static/web/piweb/.piget/skippaths
lawwenda/asset/-static/web/piweb/.piget/version
lawwenda/asset/-static/web/piweb/3rdparty/leaflet/leaflet.css
lawwenda/asset/-static/web/piweb/3rdparty/leaflet/leaflet.js
lawwenda/asset/-static/web/piweb/3rdparty/leaflet/images/layers-2x.png
lawwenda/asset/-static/web/piweb/3rdparty/leaflet/images/layers.png
lawwenda/asset/-static/web/piweb/3rdparty/leaflet/images/marker-icon-2x.png
lawwenda-0.4.184.dist-info/METADATA
lawwenda-0.4.184.dist-info/WHEEL
lawwenda-0.4.184.dist-info/top_level.txt
lawwenda-0.4.184.dist-info/RECORD
