Metadata-Version: 2.4
Name: lawwenda
Version: 0.4.184
Summary: web file manager
Home-page: https://pseudopolis.eu/pino/lawwenda
Author: Josef Hahn
Author-email: lawwenda@pseudopolis.eu
License: AGPL 3
Keywords: python web share file manager system
Requires-Dist: werkzeug
Requires-Dist: Pillow
Requires-Dist: xattr
Dynamic: author
Dynamic: author-email
Dynamic: description
Dynamic: description-content-type
Dynamic: home-page
Dynamic: keywords
Dynamic: license
Dynamic: requires-dist
Dynamic: summary
